granite/__init__.py
granite/studio.html
granyte-0.1.6.dist-info/METADATA
granyte-0.1.6.dist-info/WHEEL
granyte-0.1.6.dist-info/licenses/LICENSE
granyte-0.1.6.dist-info/RECORD
