Metadata-Version: 2.4
Name: granyte
Version: 0.1.6
Summary: A minimal demo package
Project-URL: Repository, https://github.com/UlfBissbort/granite-sdk-python
Author: Ulf Bissbort
License-File: LICENSE
Requires-Python: >=3.8
